pypeliner/__init__.py
pypeliner/_version.py
pypeliner/app.py
pypeliner/arguments.py
pypeliner/commandline.py
pypeliner/containerize.py
pypeliner/database.py
pypeliner/deep.py
pypeliner/delegator.py
pypeliner/flyweight.py
pypeliner/graph.py
pypeliner/helpers.py
pypeliner/identifiers.py
pypeliner/jobs.py
pypeliner/managed.py
pypeliner/resources.py
pypeliner/runskip.py
pypeliner/sandbox.py
pypeliner/scheduler.py
pypeliner/sqlitedb.py
pypeliner/storage.py
pypeliner/workflow.py
pypeliner/contrib/__init__.py
pypeliner/contrib/aws/__init__.py
pypeliner/contrib/aws/aws_batch.py
pypeliner/contrib/aws/aws_storage.py
pypeliner/contrib/aws/batchqueue.py
pypeliner/contrib/aws/fetch_run.py
pypeliner/contrib/aws/helpers.py
pypeliner/contrib/aws/objectstorage.py
pypeliner/contrib/azure/__init__.py
pypeliner/contrib/azure/batchclient.py
pypeliner/contrib/azure/batchqueue.py
pypeliner/contrib/azure/blobclient.py
pypeliner/contrib/azure/blobstorage.py
pypeliner/contrib/azure/rabbitmq.py
pypeliner/execqueue/__init__.py
pypeliner/execqueue/base.py
pypeliner/execqueue/drmaa.py
pypeliner/execqueue/factory.py
pypeliner/execqueue/local.py
pypeliner/execqueue/qcmd.py
pypeliner/execqueue/qsub.py
pypeliner/execqueue/subproc.py
pypeliner/execqueue/utils.py
pypeliner/tests/__init__.py
pypeliner/tests/jobs.py
pypeliner/tests/scheduler_test.1.input
pypeliner/tests/scheduler_test.2.input
pypeliner/tests/scheduler_test.input
pypeliner/tests/tasks.py
pypeliner/tests/test_queue.py
pypeliner/tests/test_scheduler.py
pypeliner-0.5.24.dist-info/LICENSE.txt
pypeliner-0.5.24.dist-info/METADATA
pypeliner-0.5.24.dist-info/WHEEL
pypeliner-0.5.24.dist-info/entry_points.txt
pypeliner-0.5.24.dist-info/top_level.txt
pypeliner-0.5.24.dist-info/RECORD
