Metadata-Version: 2.1
Name: pypeliner
Version: 0.5.24
Summary: A library for creating informatic workflows or pipelines.
Home-page: http://bitbucket.org/dranew/pypeliner
Author: Andrew McPherson
Author-email: andrew.mcpherson@gmail.com
License: UNKNOWN
Download-URL: https://bitbucket.org/dranew/pypeliner/get/v0.5.24.tar.gz
Keywords: scientific,framework
Platform: UNKNOWN
Requires-Dist: dill
Requires-Dist: networkx
Requires-Dist: pyyaml
Requires-Dist: six
